biowdl_input_converter/__init__.py
biowdl_input_converter/input_conversions.py
biowdl_input_converter/output_conversions.py
biowdl_input_converter/samplestructure.py
biowdl_input_converter/utils.py
biowdl_input_converter-0.3.0.dist-info/LICENSE
biowdl_input_converter-0.3.0.dist-info/METADATA
biowdl_input_converter-0.3.0.dist-info/WHEEL
biowdl_input_converter-0.3.0.dist-info/entry_points.txt
biowdl_input_converter-0.3.0.dist-info/top_level.txt
biowdl_input_converter-0.3.0.dist-info/RECORD
