Metadata-Version: 2.1
Name: biowdl-input-converter
Version: 0.3.0
Summary: Converting various input formats into WDL structs for BioWDL pipelines.
Home-page: https://github.com/biowdl/biowdl-input-converter
Author: Leiden University Medical Center
Author-email: sasc@lumc.nl
License: MIT
Keywords: biowdl pipeline input csv yaml json samplesheet convert
Platform: UNKNOWN
Classifier: Programming Language :: Python :: 3 :: Only
Classifier: Programming Language :: Python :: 3
Classifier: Programming Language :: Python :: 3.7
Classifier: Programming Language :: Python :: 3.8
Classifier: Programming Language :: Python :: 3.9
Classifier: License :: OSI Approved :: MIT License
Requires-Python: >=3.7
Requires-Dist: pyyaml
